starlette_static_resources/__init__.py
starlette_static_resources/staticresources.py
starlette_static_resources-0.1.2.dist-info/WHEEL
starlette_static_resources-0.1.2.dist-info/METADATA
starlette_static_resources-0.1.2.dist-info/RECORD
